reqtestium/__init__.py
reqtestium/api_client.py
reqtestium/api_response.py
reqtestium/configuration.py
reqtestium/loggers/__init__.py
reqtestium/loggers/allure_logger.py
reqtestium/loggers/console_logger.py
reqtestium/loggers/logger.py
reqtestium/utils.py
reqtestium-0.10.0.dist-info/METADATA
reqtestium-0.10.0.dist-info/WHEEL
reqtestium-0.10.0.dist-info/RECORD
