Metadata-Version: 2.3
Name: reqtestium
Version: 0.10.0
Summary: 
License: MIT
Author: John Makarov
Author-email: johnmakarovqa@gmail.com
Requires-Python: >=3.12,<4.0
Classifier: License :: OSI Approved :: MIT License
Classifier: Programming Language :: Python :: 3
Classifier: Programming Language :: Python :: 3.12
Classifier: Programming Language :: Python :: 3.13
Requires-Dist: allure-pytest (>=2.13.5,<3.0.0)
Requires-Dist: curlify (>=2.2.1,<3.0.0)
Requires-Dist: deepdiff (>=8.2.0,<9.0.0)
Requires-Dist: jsonschema (>=4.23.0,<5.0.0)
Requires-Dist: requests (>=2.32.3,<3.0.0)
